odoo/addons/sms_no_alter_body/README.rst
odoo/addons/sms_no_alter_body/__init__.py
odoo/addons/sms_no_alter_body/__manifest__.py
odoo/addons/sms_no_alter_body/i18n/es.po
odoo/addons/sms_no_alter_body/i18n/it.po
odoo/addons/sms_no_alter_body/i18n/sms_no_alter_body.pot
odoo/addons/sms_no_alter_body/models/__init__.py
odoo/addons/sms_no_alter_body/models/mail_thread.py
odoo/addons/sms_no_alter_body/models/sms_sms.py
odoo/addons/sms_no_alter_body/readme/CONTRIBUTORS.rst
odoo/addons/sms_no_alter_body/readme/DESCRIPTION.rst
odoo/addons/sms_no_alter_body/static/description/icon.png
odoo/addons/sms_no_alter_body/static/description/index.html
odoo/addons/sms_no_alter_body/tests/__init__.py
odoo/addons/sms_no_alter_body/tests/test_sms_no_alter_body.py
odoo14_addon_sms_no_alter_body-14.0.1.0.1.dev10.dist-info/METADATA
odoo14_addon_sms_no_alter_body-14.0.1.0.1.dev10.dist-info/WHEEL
odoo14_addon_sms_no_alter_body-14.0.1.0.1.dev10.dist-info/top_level.txt
odoo14_addon_sms_no_alter_body-14.0.1.0.1.dev10.dist-info/RECORD
